rnd_upload/__init__.py
rnd_upload/rnd_upload.py
rnd_upload-2.0.dist-info/LICENSE
rnd_upload-2.0.dist-info/METADATA
rnd_upload-2.0.dist-info/WHEEL
rnd_upload-2.0.dist-info/top_level.txt
rnd_upload-2.0.dist-info/RECORD
